met_estimator/METs.py
met_estimator/__init__.py
met_estimator/cutpoints.py
met_estimator/driver.py
met_estimator/sojourn.py
met_estimator/utils.py
met_estimator-0.2.dist-info/DESCRIPTION.rst
met_estimator-0.2.dist-info/METADATA
met_estimator-0.2.dist-info/RECORD
met_estimator-0.2.dist-info/WHEEL
met_estimator-0.2.dist-info/metadata.json
met_estimator-0.2.dist-info/top_level.txt
