Metadata-Version: 2.0
Name: met-estimator
Version: 0.2
Summary: Estimate and classify activity based on accelerometer input
Home-page: http://github.com/ms2300/met_estimator
Author: ms2300
Author-email: matt.sewall@gmail.com
License: MIT
Platform: UNKNOWN
Requires-Dist: numpy
